s2py/__init__.py
s2py/lib.py
s2py-0.1.2.dist-info/WHEEL
s2py-0.1.2.dist-info/METADATA
s2py-0.1.2.dist-info/RECORD
